simplyhack.py
simplyhack-0.0.10.dist-info/METADATA
simplyhack-0.0.10.dist-info/WHEEL
simplyhack-0.0.10.dist-info/top_level.txt
simplyhack-0.0.10.dist-info/RECORD
