Metadata-Version: 2.1
Name: simplyhack
Version: 0.0.10
Summary: Simplyfing the process of creating cybersecurity tools
Home-page: UNKNOWN
Author: Abhishek Uday Dangat
Author-email: abshdangat@gmail.com
License: UNKNOWN
Keywords: python,hacking,cybersecurity,hacking tools,security testing,hacker
Platform: UNKNOWN
Classifier: Development Status :: 1 - Planning
Classifier: Intended Audience :: Developers
Classifier: Programming Language :: Python :: 3
Classifier: Operating System :: Unix
Classifier: Operating System :: MacOS :: MacOS X
Classifier: Operating System :: Microsoft :: Windows
Requires-Dist: colorama
Requires-Dist: pikepdf
Requires-Dist: rarfile
Requires-Dist: scapy
Requires-Dist: scapy-http
